darca_exception/__init__.py
darca_exception/__version__.py
darca_exception/exception.py
darca_exception-0.1.1.dist-info/LICENSE
darca_exception-0.1.1.dist-info/METADATA
darca_exception-0.1.1.dist-info/WHEEL
darca_exception-0.1.1.dist-info/RECORD
